sagepy/__init__.py
sagepy/core/__init__.py
sagepy/core/database.py
sagepy/core/enzyme.py
sagepy/core/fasta.py
sagepy/core/fdr.py
sagepy/core/ion_series.py
sagepy/core/lfq.py
sagepy/core/mass.py
sagepy/core/ml/__init__.py
sagepy/core/ml/mobility_model.py
sagepy/core/ml/pep.py
sagepy/core/ml/retention_alignment.py
sagepy/core/ml/retention_model.py
sagepy/core/modification.py
sagepy/core/peptide.py
sagepy/core/scoring.py
sagepy/core/spectrum.py
sagepy/core/tmt.py
sagepy/core/unimod.py
sagepy/qfdr/__init__.py
sagepy/qfdr/tdc.py
sagepy/rescore/__init__.py
sagepy/rescore/lda.py
sagepy/rescore/rescore.py
sagepy/rescore/rt_predictor.py
sagepy/rescore/utility.py
sagepy/utility.py
sagepy-0.3.13.dist-info/METADATA
sagepy-0.3.13.dist-info/WHEEL
sagepy-0.3.13.dist-info/RECORD
