Metadata-Version: 2.4
Name: sagepy
Version: 0.3.13
Summary: 
Author: theGreatHerrLebert
Author-email: davidteschner@googlemail.com
Requires-Python: >=3.10
Classifier: Programming Language :: Python :: 3
Classifier: Programming Language :: Python :: 3.10
Classifier: Programming Language :: Python :: 3.11
Classifier: Programming Language :: Python :: 3.12
Classifier: Programming Language :: Python :: 3.13
Classifier: Programming Language :: Python :: 3.14
Requires-Dist: lxml (>=5.3.0)
Requires-Dist: mokapot (>=0.10.0)
Requires-Dist: numba (>=0.59.1)
Requires-Dist: numpy (==1.26.4)
Requires-Dist: pandas (>=1.3.3)
Requires-Dist: pyteomics (>=4.7.3)
Requires-Dist: sagepy-connector (>=0.3.13)
Requires-Dist: scikit-learn (>=1.6.1)
Requires-Dist: tqdm (>=4.62.3)
